{
  "Plotter" :
  [
    {
      "MultiHeaderSeriesPlotter":
      {
        "PlotConfig":
        {
          "OutputPathOverride": "./docs/html/plots/Respiratory/", "ImageProperties": { "DimensionMode": "Square" },
          "SciLimits": {}
        },
        "PlotSource":
        [
          { "CSVData": "./verification/scenarios/validation/systems/RespiratoryValidation-StandardMaleResults.csv" }
        ],
        "Series":
        [
          { "Title": "Engine Pulmonary Compliance", "XHeader": "LeftPleuralCavity-Pressure(cmH2O)", "YHeader": [ "TotalLungVolume(mL)" ] }
        ]
      }
    },
    {
      "MultiHeaderSeriesPlotter":
      {
        "PlotConfig":
        {
          "OutputPathOverride": "./docs/html/plots/Respiratory/", "ImageProperties": { "DimensionMode": "Square" },
          "LegendMode": "NoLegends", "SciLimits": {}
        },
        "PlotSource":
        [
          { "CSVData": "$VALIDATION_DIR/Waveforms/PulmonaryCompliance_Guyton.csv" }
        ],
        "Series":
        [
          { "Title": "Guyton Pulmonary Compliance", "XHeader": "PleuralPressure(cmH2O)", "YHeader": [ "LungVolume(L)" ] }
        ]
      }
    },
    {
      "MultiHeaderSeriesPlotter":
      {
        "PlotConfig":
        {
          "OutputPathOverride": "./docs/html/plots/Respiratory/", "ImageProperties": { "DimensionMode": "Square" },
          "SciLimits": {}
        },
        "PlotSource":
        [
          { "CSVData": "./verification/scenarios/miscellaneous/ComplianceCurveResults.csv" }
        ],
        "Series":
        [
          { "Title": "Experimental Pulmonary Compliance", "XHeader": "IntrapulmonaryPressure(cmH2O)", "YHeader": [ "TotalLungVolume(mL)" ] }
        ]
      }
    },
    {
      "MultiHeaderSeriesPlotter":
      {
        "PlotConfig":
        {
          "Gridlines": true, "OutputPathOverride": "./docs/html/plots/Cardiovascular", "PercentOfBaselineMode": "All",
          "TickStyle": "Plain"
        },
        "PlotSource":
        [
          { "CSVData": "./verification/scenarios/patient/HemorrhageClass4NoFluidResults.csv" }
        ],
        "ValidationSource":
        {
          "CSVData": "$VALIDATION_DIR/Cardiovascular/HemorrhagicCardiacOutputShockValidation.csv"
        },
        "Series":
        [
          { "Title": "", "OutputFilename": "CardiacOutputShock_partial",
              "XHeader": "BloodVolume(L)", "XLabel": "Percent Of Blood Loss", "XBounds": { "LowerBound": 0, "UpperBound": 50 },
              "YHeader": [ "CardiacOutput(L/min)" ], "YBounds": { "LowerBound": 0, "UpperBound": 105 }, "YLabel": "Pulse Normalized Cardiac Output",
              "X2Header": "BloodVolumeLost(%)", "Y2Header": [ "NormalizedCardiacOutput" ], "Y2Label": "Validation Normalized Cardiac Output",
              "Y2Bounds": { "LowerBound": 0, "UpperBound": 105 }}
        ]
      }
    },
    {
      "MultiHeaderSeriesPlotter":
      {
        "PlotConfig":
        {
          "Gridlines": true, "OutputPathOverride": "./docs/html/plots/Cardiovascular", "PercentOfBaselineMode": "OnlyY",
          "TickStyle": "Plain"
        },
        "PlotSource":
        [
          { "CSVData": "./verification/scenarios/patient/HemorrhageGroup1Results.csv", "Label": "Group 1" },
          { "CSVData": "./verification/scenarios/patient/HemorrhageGroup2Results.csv", "Label": "Group 2" },
          { "CSVData": "./verification/scenarios/patient/HemorrhageGroup3Results.csv", "Label": "Group 3" },
          { "CSVData": "./verification/scenarios/patient/HemorrhageGroup4Results.csv", "Label": "Group 4" },
          { "CSVData": "./verification/scenarios/patient/HemorrhageGroup5Results.csv", "Label": "Group 5" },
          { "CSVData": "./verification/scenarios/patient/HemorrhageGroup6Results.csv", "Label": "Group 6" }
        ],
        "Series":
        [
          { "Title": "", "OutputFilename": "HemorrhageGroups_partial", "XHeader": "Time(s)",
              "YHeader": [ "MeanArterialPressure(mmHg)" ], "YLabel": "Mean Arterial Pressure Delta",
              "YBounds": { "LowerBound": 0, "UpperBound": 105 } }
        ]
      }
    },
    {
      "MultiHeaderSeriesPlotter":
      {
        "PlotConfig":
        {
          "Gridlines": true, "OutputPathOverride": "./docs/html/plots/Cardiovascular/", "TickStyle": "Plain"
        },
        "PlotSource":
        [
          { "CSVData": "./verification/unit_tests/pulse/CardiovascularCircuitOutput.csv" }
        ],
        "Series":
        [
          { "Title": "", "OutputFilename": "ComplianceVsElastance_partial", "XBounds": { "LowerBound": 30, "UpperBound": 35 },
              "YHeader": [ "LeftHeartCompliance_mL_Per_mmHg" ], "Y2Header": [ "LeftHeartElastance_mmHg_Per_mL" ] }
        ]
      }
    },
    {
      "MultiHeaderSeriesPlotter":
      {
        "PlotConfig":
        {
          "OutputPathOverride": "./docs/html/plots/Cardiovascular/", "PlotEvents": true, "TickStyle": "Plain"
        },
        "PlotSource":
        [
          { "CSVData": "./verification/scenarios/patient/VentricularSystolicDysfunctionResults.csv" }
        ],
        "Series":
        [
          { "Title": "", "OutputFilename": "HeartFailure_partial", "YHeader": [ "BloodVolume(L)" ] }
        ]
      }
    },
    {
      "MultiHeaderSeriesPlotter":
      {
        "PlotConfig":
        {
          "Gridlines": true, "OutputPathOverride": "./docs/html/plots/Endocrine/", "PlotActions": true, "PlotEvents": true,
          "LegendMode": "NoLegends", "TickStyle": "Plain"
        },
        "PlotSource":
        [
          { "CSVData": "./verification/scenarios/patient/AcuteStressResults.csv" }
        ],
        "Series":
        [
          { "Title": "Epinephrine Blood Concentration", "OutputFilename": "AcuteStressBloodEpi_partial",
              "YHeader": [ "Aorta-Epinephrine-Concentration(ug/L)" ] },
          { "Title": "Heart Rate", "OutputFilename": "AcuteStressHR_partial",
              "YHeader": [ "HeartRate(1/min)" ] },
          { "Title": "Systolic Pressure", "OutputFilename": "AcuteStressSystolic_partial",
              "YHeader": [ "SystolicArterialPressure(mmHg)" ] },
          { "Title": "Diastolic Pressure", "OutputFilename": "AcuteStressDiastolic_partial",
              "YHeader": [ "DiastolicArterialPressure(mmHg)" ] },
          { "OutputFilename": "AcuteStressLegend_partial",
              "PlotConfig": { "LegendMode": "OnlyActionEventLegend", "PlotEvents": false, "ImageProperties": { "DimensionMode": "Legend" } } }
        ]
      }
    },
    {
      "MultiHeaderSeriesPlotter":
      {
        "PlotConfig":
        {
          "Gridlines": true, "OutputPathOverride": "./docs/html/plots/Drugs/", "TickStyle": "Plain"
        },
        "PlotSource":
        [
          { "CSVData": "./verification/scenarios/validation/drugs/AlbuterolValidationResults.csv", "LineFormat": "-b" }
        ],
        "ValidationSource": { "CSVData": "$VALIDATION_DIR/Pharmacokinetic/CSVs/Albuterol.csv", "LineFormat": "Dr" },
        "Series":
        [
          { "Title": "Albuterol", "OutputFilename": "Albuterol_partial",
              "YHeader": [ "Albuterol-PlasmaConcentration(ug/L)" ], "YBounds": { "UpperBound": 2.6 },
              "Y2Header": [ "PlasmaConcentration(ug/L)" ], "Y2Bounds": { "UpperBound": 2.6 },
              "Y2Label": "Experimental PlasmaConcentration(ug/L)" }
        ]
      }
    },
    {
      "MultiHeaderSeriesPlotter":
      {
        "PlotConfig":
        {
          "Gridlines": true, "OutputPathOverride": "./docs/html/plots/Cardiovascular/",
          "ImageProperties": { "Height_inch": 6, "Width_inch": 4 }, "SciLimits": {}, "LegendMode": "NoLegends", "ZeroAxis": true
        },
        "PlotSource":
        [
          { "CSVData": "./verification/scenarios/validation/systems/CardiovascularValidation-StandardMaleResults.csv" }
        ],
        "Series":
        [
          { "OutputFilename": "PVLoop_partial", "Title": "", "XHeader": "LeftHeart-Volume(mL)", "YHeader": [ "LeftHeart-Pressure(mmHg)" ] }
        ]
      }
    }
  ]
}
